almgren_chriss/__init__.py
almgren_chriss/cost.py
almgren_chriss/decay_rate.py
almgren_chriss/trade.py
almgren_chriss-1.1.0.dist-info/LICENSE
almgren_chriss-1.1.0.dist-info/METADATA
almgren_chriss-1.1.0.dist-info/WHEEL
almgren_chriss-1.1.0.dist-info/RECORD
