Metadata-Version: 2.1
Name: almgren-chriss
Version: 1.1.0
Summary: functions for implementing the Almgren-Chriss model for optimal execution of portfolio transactions.
License: GNU General Public License
Keywords: optimal exeuction,quantitative finance,Almgren Chriss
Author: Bernardo Paulsen
Author-email: paulsen.bernardo@gmail.com
Requires-Python: >=3.10,<4.0
Classifier: License :: Other/Proprietary License
Classifier: Programming Language :: Python :: 3
Classifier: Programming Language :: Python :: 3.10
Classifier: Programming Language :: Python :: 3.11
Requires-Dist: numpy (>=1.0,<2.0)
Project-URL: Documentation, https://bernardopaulsen.github.io/almgren-chriss/
Project-URL: GitHub, https://github.com/bernardopaulsen/almngren-chriss
